minihelper/.DS_Store
minihelper/google/__init__.py
minihelper/google/bigquery.py
minihelper/google/spark/__init__.py
minihelper/google/spark/bigquery.py
minihelper/google/spark/storage.py
minihelper/google/storage.py
minihelper-0.1.5.dist-info/METADATA
minihelper-0.1.5.dist-info/WHEEL
minihelper-0.1.5.dist-info/RECORD
